data_transformation_yfhsi/__init__.py
data_transformation_yfhsi/data_transformation.py
data_transformation_yfhsi/validations.py
data_transformation_yfhsi-0.18.1a0.dist-info/METADATA
data_transformation_yfhsi-0.18.1a0.dist-info/WHEEL
data_transformation_yfhsi-0.18.1a0.dist-info/RECORD
