Metadata-Version: 2.1
Name: data-transformation-yfhsi
Version: 0.18.1a0
Summary: Data Transfomation Libraries. Transpose. Time Series Windowing. Cross Correlation
Author: skaival
Author-email: you@example.com
Requires-Python: >=3.11,<4.0
Classifier: Programming Language :: Python :: 3
Classifier: Programming Language :: Python :: 3.11
Classifier: Programming Language :: Python :: 3.12
Requires-Dist: numpy (>=1.26.4,<2.0.0)
